incenp/__init__.py
incenp/certbot/__init__.py
incenp/certbot/acme-challenge.sh
incenp/certbot/ssh.py
incenp.certbot.ssh-0.2.3.dist-info/LICENSE
incenp.certbot.ssh-0.2.3.dist-info/METADATA
incenp.certbot.ssh-0.2.3.dist-info/NOTICE
incenp.certbot.ssh-0.2.3.dist-info/WHEEL
incenp.certbot.ssh-0.2.3.dist-info/entry_points.txt
incenp.certbot.ssh-0.2.3.dist-info/top_level.txt
incenp.certbot.ssh-0.2.3.dist-info/RECORD
