Metadata-Version: 2.1
Name: incenp.certbot.ssh
Version: 0.2.3
Summary: Certbot SSH authenticator plugin
Home-page: https://git.incenp.org/damien/certbot-ssh
Author: Damien Goutte-Gattat
Author-email: dgouttegattat@incenp.org
License: Apache License 2.0
Platform: UNKNOWN
Classifier: Development Status :: 4 - Beta
Classifier: Environment :: Console
Classifier: Intended Audience :: System Administrators
Classifier: License :: OSI Approved :: Apache Software License
Classifier: Programming Language :: Python :: 2.7
Classifier: Programming Language :: Python :: 3.6
Classifier: Programming Language :: Python :: 3.7
